vanitaspy/__init__.py
vanitas_antispam-1.0.1.dist-info/LICENSE
vanitas_antispam-1.0.1.dist-info/METADATA
vanitas_antispam-1.0.1.dist-info/WHEEL
vanitas_antispam-1.0.1.dist-info/top_level.txt
vanitas_antispam-1.0.1.dist-info/RECORD
